canaverall/__init__.py
canaverall/__main__.py
canaverall/cli.py
canaverall/create_oam.py
canaverall/merge_oam.py
canaverall/oam_form.py
canaverall/templates/vela_default.yaml
canaverall/templates/vela_template.yaml
canaverall-0.1.0.dist-info/LICENSE
canaverall-0.1.0.dist-info/METADATA
canaverall-0.1.0.dist-info/WHEEL
canaverall-0.1.0.dist-info/entry_points.txt
canaverall-0.1.0.dist-info/RECORD
